spaceformers/__init__.py
spaceformers-0.0.1.dist-info/METADATA
spaceformers-0.0.1.dist-info/WHEEL
spaceformers-0.0.1.dist-info/top_level.txt
spaceformers-0.0.1.dist-info/RECORD
