Metadata-Version: 2.4
Name: spaceformers
Version: 0.0.1
Summary: spaceformers - turn any space into a scene...
Author-email: Yunus Skeete <yunus@spatial-intelligence.co.uk>
Classifier: Development Status :: 1 - Planning
Classifier: Programming Language :: Python :: 3
Requires-Python: >=3.9
